BBAWSLightsailMiniAIV1aStack/__init__.py
BBAWSLightsailMiniAIV1aStack/bb_aws_lightsail_mini_ai_v1a.py
bbawslightsailminiaiv1a-1.0.2.dist-info/METADATA
bbawslightsailminiaiv1a-1.0.2.dist-info/WHEEL
bbawslightsailminiaiv1a-1.0.2.dist-info/top_level.txt
bbawslightsailminiaiv1a-1.0.2.dist-info/RECORD
