Metadata-Version: 2.4
Name: BBAWSLightsailMiniAIV1a
Version: 1.0.2
Summary: Buzzerboy Architecture for Deploying AI-Enhanced Web Applications on AWS LightSail with Bedrock
Home-page: https://www.buzzerboy.com/
Author: Buzzerboy Inc
Author-email: Buzzerboy Inc <info@buzzerboy.com>
Project-URL: Homepage, https://www.buzzerboy.com/
Project-URL: Issues, https://dev.azure.com/buzzerboyinc/buzzerboy
Classifier: Programming Language :: Python :: 3
Classifier: License :: OSI Approved :: MIT License
Classifier: Operating System :: OS Independent
Requires-Python: >=3.8
Requires-Dist: cdktf<1.0,>=0.17.0
Requires-Dist: constructs<11.0,>=10.0.0
Requires-Dist: cdktf-cdktf-provider-aws>=12.0.0
Requires-Dist: cdktf-cdktf-provider-random>=8.0.0
Requires-Dist: cdktf-cdktf-provider-null>=10.0.0
Requires-Dist: toml
Requires-Dist: pipenv
Requires-Dist: BuzzerboyArchetype
Requires-Dist: BBAWSLightsailMiniV1a
Requires-Dist: BBAWSLightsailMiniV1a
Dynamic: author
Dynamic: home-page
Dynamic: requires-dist
Dynamic: requires-python
